Workbook

Sheet INSTRUCTIONS
A1: CAPSERIESX CAPITAL EXPENDITURE PLANNER
A2: 5-Year & 10-Year Capital Planning with Reserve Fund Analysis
A4: Version: 1.0 | Last Updated: December 2024 | © DeFi Assets LLC
A6: PURPOSE & OVERVIEW
A8: This template helps you plan, budget, and track capital expenditures (CapEx) over your investment holding period.
A9: Proper CapEx planning is CRITICAL for accurate return projections and avoiding unexpected capital calls.
A11: WHAT THIS TEMPLATE INCLUDES:
A12: • Major Systems Inventory - Track age, condition, and replacement costs for all major systems
A13: • Replacement Schedule - Automatic scheduling based on useful life
A14: • 5-Year CapEx Plan - Detailed year-by-year capital budget (required for Gold+)
A15: • 10-Year CapEx Plan - Extended planning horizon (required for Gold+)
A16: • Reserve Fund Calculator - Determine required capital reserves
... A93: Need contractor cost estimates? Use HomeAdvisor, Angi, or local contractors

Sheet SUMMARY
A1: CAPITAL EXPENDITURE PLAN - SUMMARY
A3: Property Name: | B3: =Property_Info!B4 -> 0
A4: Property Value: | B4: =Property_Info!B10 -> 0 | D4: Hold Period: | E4: =Property_Info!B12&" years" -> years
A6: CAPITAL EXPENDITURE OVERVIEW
A7: Total Replacement Value (All Systems): | B7: =Systems_Inventory!E22 -> 0
A8: 5-Year Planned CapEx: | B8: TBD - Sum from 5-Year Plan
A9: 10-Year Planned CapEx: | B9: ='10_Year_CapEx_Plan'!C15 -> 0
A11: Annual Reserve Recommendation: | B11: =Property_Info!B19 -> 0
A12: Reserve as % of Property Value: | B12: =Property_Info!B18 -> 0
A14: IMMEDIATE CAPEX NEEDS (< 1 YEAR)
A15: System | B15: Current Condition | C15: Replacement Cost | D15: Priority
A22: MAJOR UPCOMING PROJECTS (Years 1-5)
A23: Year | B23: Project Description | C23: Estimated Cost | D23: Funding Source
A34: RESERVE FUND ADEQUACY ASSESSMENT
A35: Are capital reserves adequate for identified needs?
A36: Supporting Analysis:
A38: KEY CAPEX RISKS
A39: 1.
A40: 2.
A41: 3.
A43: RECOMMENDATIONS

Sheet Property_Info
A1: PROPERTY INFORMATION
A3: Property Name:
A4: Property Address:
A6: Total Units:
A7: Total Building SF:
A8: Year Built:
A9: Property Type:
A11: Purchase Price:
A12: Current Property Value:
A13: Acquisition Date:
A14: Planned Hold Period (years):
A16: RESERVE FUND GUIDELINES
A17: Annual Reserve % of Value: | C17: 1-2% typical, 2-3% for older properties
A18: Recommended Annual Reserve: | B18: =B10*0.02 -> 0
A19: Per Unit Annual Reserve:

Sheet Systems_Inventory
A1: MAJOR SYSTEMS INVENTORY & REPLACEMENT COSTS
A2: Document all major building systems. This drives your replacement schedule and reserve calculations.
A4: System/Component | B4: Current Age | C4: Useful Life | D4: Condition | E4: Replacement Cost | F4: Years Until Replace | G4: Replace Year | H4: Priority
A5: Roof | C5: 20 | F5: =MAX(0,C5-B5) -> 20 | G5: =YEAR(Property_Info!$B$11)+F5 -> 1920
A6: HVAC System - Building 1 | C6: 15 | F6: =MAX(0,C6-B6) -> 15 | G6: =YEAR(Property_Info!$B$11)+F6 -> 1915
A7: HVAC System - Building 2 | C7: 15 | F7: =MAX(0,C7-B7) -> 15 | G7: =YEAR(Property_Info!$B$11)+F7 -> 1915
A8: Water Heaters | C8: 10 | F8: =MAX(0,C8-B8) -> 10 | G8: =YEAR(Property_Info!$B$11)+F8 -> 1910
A9: Plumbing System | C9: 40 | F9: =MAX(0,C9-B9) -> 40 | G9: =YEAR(Property_Info!$B$11)+F9 -> 1940
A10: Electrical System | C10: 40 | F10: =MAX(0,C10-B10) -> 40 | G10: =YEAR(Property_Info!$B$11)+F10 -> 1940
A11: Parking Lot/Driveway | C11: 20 | F11: =MAX(0,C11-B11) -> 20 | G11: =YEAR(Property_Info!$B$11)+F11 -> 1920
A12: Windows | C12: 25 | F12: =MAX(0,C12-B12) -> 25 | G12: =YEAR(Property_Info!$B$11)+F12 -> 1925
A13: Exterior Doors | C13: 25 | F13: =MAX(0,C13-B13) -> 25 | G13: =YEAR(Property_Info!$B$11)+F13 -> 1925
A14: Flooring (common areas) | C14: 15 | F14: =MAX(0,C14-B14) -> 15 | G14: =YEAR(Property_Info!$B$11)+F14 -> 1915
A15: Appliances (units) | C15: 12 | F15: =MAX(0,C15-B15) -> 12 | G15: =YEAR(Property_Info!$B$11)+F15 -> 1912
A16: Exterior Paint/Siding | C16: 15 | F16: =MAX(0,C16-B16) -> 15 | G16: =YEAR(Property_Info!$B$11)+F16 -> 1915
... A21: Fire Safety System | C21: 20 | F21: =MAX(0,C21-B21) -> 20 | G21: =YEAR(Property_Info!$B$11)+F21 -> 1920
A22: TOTAL REPLACEMENT COST (All Systems) | E22: =SUM(E5:E21) -> 0

Sheet 5_Year_CapEx_Plan
A1: 5-YEAR CAPITAL EXPENDITURE PLAN
A2: Plan capital expenditures for each year. Include both scheduled replacements and planned improvements.
A4: Annual Inflation Rate for Costs: | B4: 0.03
A6: YEAR 1
A7: Item/Project | B7: Category | C7: Estimated Cost | D7: Timing | E7: Contractor | F7: Priority | G7: Notes
A18: YEAR 1 TOTAL: | C18: =SUM(C8:C17) -> 0
A20: YEAR 2
A21: Item/Project | B21: Category | C21: Estimated Cost | D21: Timing | E21: Contractor | F21: Priority | G21: Notes
A32: YEAR 2 TOTAL: | C32: =SUM(C22:C31) -> 0
A34: YEAR 3
A35: Item/Project | B35: Category | C35: Estimated Cost | D35: Timing | E35: Contractor | F35: Priority | G35: Notes
A46: YEAR 3 TOTAL: | C46: =SUM(C36:C45) -> 0
A48: YEAR 4
A49: Item/Project | B49: Category | C49: Estimated Cost | D49: Timing | E49: Contractor | F49: Priority | G49: Notes
A60: YEAR 4 TOTAL: | C60: =SUM(C50:C59) -> 0
A62: YEAR 5
A63: Item/Project | B63: Category | C63: Estimated Cost | D63: Timing | E63: Contractor | F63: Priority | G63: Notes
A74: YEAR 5 TOTAL: | C74: =SUM(C64:C73) -> 0
A76: 5-YEAR TOTAL CAPEX:

Sheet 10_Year_CapEx_Plan
A1: 10-YEAR CAPITAL EXPENDITURE PLAN
A2: Extended 10-year capital planning. Required for Gold and Platinum partners.
A4: Year | B4: Major Projects | C4: Estimated Cost | D4: Inflated Cost | E4: Reserve Balance | F4: Notes
A5: 1 | D5: =C5*POWER(1.03,0) -> 0
A6: 2 | D6: =C6*POWER(1.03,1) -> 0
A7: 3 | D7: =C7*POWER(1.03,2) -> 0
A8: 4 | D8: =C8*POWER(1.03,3) -> 0
A9: 5 | D9: =C9*POWER(1.03,4) -> 0
A10: 6 | D10: =C10*POWER(1.03,5) -> 0
A11: 7 | D11: =C11*POWER(1.03,6) -> 0
A12: 8 | D12: =C12*POWER(1.03,7) -> 0
A13: 9 | D13: =C13*POWER(1.03,8) -> 0
A14: 10 | D14: =C14*POWER(1.03,9) -> 0
A15: TOTAL 10-YEAR: | C15: =SUM(C5:C14) -> 0 | D15: =SUM(D5:D14) -> 0
