Workbook

Sheet INSTRUCTIONS
A1: CAPSERIESX OPERATING EXPENSE ESTIMATOR
A2: Detailed OpEx Analysis with Industry Benchmarking
A4: Version: 1.0 | Last Updated: December 2024 | © DeFi Assets LLC
A6: PURPOSE & OVERVIEW
A8: This template helps you estimate, analyze, and benchmark operating expenses for your property investment.
A9: Accurate OpEx estimation is CRITICAL for realistic NOI projections and investment underwriting.
A11: WHAT THIS TEMPLATE INCLUDES:
A12: • Complete OpEx Category Breakdown - All major expense categories with detailed line items
A13: • Industry Benchmarks - National averages by property type and class
A14: • Per Unit & Per SF Analysis - Normalize expenses for comparison
A15: • OpEx Ratio Calculator - Compare your expenses to gross income
A16: • Variance Analysis - See where you're above/below market averages
... A92: Need help finding benchmarks? See Market Research Template

Sheet SUMMARY
A1: OPERATING EXPENSE ANALYSIS - SUMMARY
A3: Property Name: | B3: =Property_Info!B4
A4: Property Type: | B4: =Property_Info!B11 | D4: Asset Class: | E4: =Property_Info!B12
A5: Total Units: | B5: =Property_Info!B7 | D5: Total SF: | E5: =Property_Info!B8
A7: OPERATING EXPENSE OVERVIEW
A8: Total Annual OpEx: | B8: =Actual_Expenses!B38
A9: OpEx Per Unit: | B9: =Actual_Expenses!B40
A10: OpEx Per SF: | B10: =Actual_Expenses!B41
A11: Operating Expense Ratio: | B11: =Actual_Expenses!B39
A13: TOP 5 EXPENSE CATEGORIES
A14: Category | B14: Annual Amount | C14: % of Total OpEx | D14: Per Unit
A15: Property Taxes | B15: =Actual_Expenses!B6 | C15: =B15/Actual_Expenses!$B$38 | D15: =B15/Property_Info!$B$7
A16: Repairs & Maintenance | B16: =Actual_Expenses!B13 | C16: =B16/Actual_Expenses!$B$38 | D16: =B16/Property_Info!$B$7
A17: Property Management | B17: =Actual_Expenses!B11 | C17: =B17/Actual_Expenses!$B$38 | D17: =B17/Property_Info!$B$7
A18: Utilities (total) | B18: =SUM(Actual_Expenses!B17:B20) | C18: =B18/Actual_Expenses!$B$38 | D18: =B18/Property_Info!$B$7
A19: Insurance | B19: =Actual_Expenses!B7 | C19: =B19/Actual_Expenses!$B$38 | D19: =B19/Property_Info!$B$7
A22: BENCHMARK ASSESSMENT
A23: Overall OpEx vs Market:
A24: OpEx Ratio Assessment:
A26: RED FLAGS / CONCERNS
A27: 1.
A28: 2.
A29: 3.
A30: 4.
A31: 5.
A33: RECOMMENDATIONS
A39: PROCEED WITH INVESTMENT?

Sheet Property_Info
A1: PROPERTY INFORMATION
A2: Enter basic property information. This data will be used throughout all expense calculations.
A4: A. BASIC PROPERTY DATA
A5: Property Name:
A6: Property Address:
A8: Total Units:
A9: Total Rentable SF:
A10: Avg Unit Size (SF): | B10: =B8/B7
A12: Year Built:
A13: Property Type:
A14: Asset Class:
A15: Number of Buildings:
A16: Number of Stories:
A18: B. INCOME (FOR OPEX RATIO CALCULATION)
A19: Gross Potential Income (Annual):
A20: Vacancy Rate %:
A21: Effective Gross Income (Annual): | B21: =B18*(1-B19/100)

Sheet Actual_Expenses
A1: ACTUAL OPERATING EXPENSES (T-12)
A2: Enter actual expenses from seller's trailing 12-month operating statements. Be sure to verify all numbers.
A4: Expense Category | B4: Annual Amount | C4: Per Unit | D4: Per SF | E4: % of EGI | F4: Data Source
A5: FIXED EXPENSES
A6: Property Taxes | C6: =IF(Property_Info!$B$7>0,B6/Property_Info!$B$7,0) | D6: =IF(Property_Info!$B$8>0,B6/Property_Info!$B$8,0) | E6: =IF(Property_Info!$B$23>0,B6/Property_Info!$B$23,0)
A7: Property Insurance | C7: =IF(Property_Info!$B$7>0,B7/Property_Info!$B$7,0) | D7: =IF(Property_Info!$B$8>0,B7/Property_Info!$B$8,0) | E7: =IF(Property_Info!$B$23>0,B7/Property_Info!$B$23,0)
A8: HOA/Condo Fees (if applicable) | C8: =IF(Property_Info!$B$7>0,B8/Property_Info!$B$7,0) | D8: =IF(Property_Info!$B$8>0,B8/Property_Info!$B$8,0) | E8: =IF(Property_Info!$B$23>0,B8/Property_Info!$B$23,0)
A10: VARIABLE EXPENSES
A11: Property Management | C11: =IF(Property_Info!$B$7>0,B11/Property_Info!$B$7,0) | D11: =IF(Property_Info!$B$8>0,B11/Property_Info!$B$8,0) | E11: =IF(Property_Info!$B$23>0,B11/Property_Info!$B$23,0)
A12: Leasing/Marketing | C12: =IF(Property_Info!$B$7>0,B12/Property_Info!$B$7,0) | D12: =IF(Property_Info!$B$8>0,B12/Property_Info!$B$8,0) | E12: =IF(Property_Info!$B$23>0,B12/Property_Info!$B$23,0)
A13: Repairs & Maintenance | C13: =IF(Property_Info!$B$7>0,B13/Property_Info!$B$7,0) | D13: =IF(Property_Info!$B$8>0,B13/Property_Info!$B$8,0) | E13: =IF(Property_Info!$B$23>0,B13/Property_Info!$B$23,0)
A14: Turnover Costs | C14: =IF(Property_Info!$B$7>0,B14/Property_Info!$B$7,0) | D14: =IF(Property_Info!$B$8>0,B14/Property_Info!$B$8,0) | E14: =IF(Property_Info!$B$23>0,B14/Property_Info!$B$23,0)
A16: UTILITIES (if owner-paid)
A17: Water & Sewer | C17: =IF(Property_Info!$B$7>0,B17/Property_Info!$B$7,0) | D17: =IF(Property_Info!$B$8>0,B17/Property_Info!$B$8,0) | E17: =IF(Property_Info!$B$23>0,B17/Property_Info!$B$23,0)
A18: Trash Removal | C18: =IF(Property_Info!$B$7>0,B18/Property_Info!$B$7,0) | D18: =IF(Property_Info!$B$8>0,B18/Property_Info!$B$8,0) | E18: =IF(Property_Info!$B$23>0,B18/Property_Info!$B$23,0)
A19: Electric (common area) | C19: =IF(Property_Info!$B$7>0,B19/Property_Info!$B$7,0) | D19: =IF(Property_Info!$B$8>0,B19/Property_Info!$B$8,0) | E19: =IF(Property_Info!$B$23>0,B19/Property_Info!$B$23,0)
A20: Gas (common area) | C20: =IF(Property_Info!$B$7>0,B20/Property_Info!$B$7,0) | D20: =IF(Property_Info!$B$8>0,B20/Property_Info!$B$8,0) | E20: =IF(Property_Info!$B$23>0,B20/Property_Info!$B$23,0)
A22: GROUNDS & EXTERIOR
A23: Landscaping/Groundskeeping | C23: =IF(Property_Info!$B$7>0,B23/Property_Info!$B$7,0) | D23: =IF(Property_Info!$B$8>0,B23/Property_Info!$B$8,0) | E23: =IF(Property_Info!$B$23>0,B23/Property_Info!$B$23,0)
A24: Snow Removal | C24: =IF(Property_Info!$B$7>0,B24/Property_Info!$B$7,0) | D24: =IF(Property_Info!$B$8>0,B24/Property_Info!$B$8,0) | E24: =IF(Property_Info!$B$23>0,B24/Property_Info!$B$23,0)
A25: Pest Control | C25: =IF(Property_Info!$B$7>0,B25/Property_Info!$B$7,0) | D25: =IF(Property_Info!$B$8>0,B25/Property_Info!$B$8,0) | E25: =IF(Property_Info!$B$23>0,B25/Property_Info!$B$23,0)
A26: Pool/Spa Service | C26: =IF(Property_Info!$B$7>0,B26/Property_Info!$B$7,0) | D26: =IF(Property_Info!$B$8>0,B26/Property_Info!$B$8,0) | E26: =IF(Property_Info!$B$23>0,B26/Property_Info!$B$23,0)
A28: ADMINISTRATIVE
A29: Accounting/Bookkeeping | C29: =IF(Property_Info!$B$7>0,B29/Property_Info!$B$7,0) | D29: =IF(Property_Info!$B$8>0,B29/Property_Info!$B$8,0) | E29: =IF(Property_Info!$B$23>0,B29/Property_Info!$B$23,0)
A30: Legal Fees | C30: =IF(Property_Info!$B$7>0,B30/Property_Info!$B$7,0) | D30: =IF(Property_Info!$B$8>0,B30/Property_Info!$B$8,0) | E30: =IF(Property_Info!$B$23>0,B30/Property_Info!$B$23,0)
A31: Office Supplies | C31: =IF(Property_Info!$B$7>0,B31/Property_Info!$B$7,0) | D31: =IF(Property_Info!$B$8>0,B31/Property_Info!$B$8,0) | E31: =IF(Property_Info!$B$23>0,B31/Property_Info!$B$23,0)
A32: Professional Fees | C32: =IF(Property_Info!$B$7>0,B32/Property_Info!$B$7,0) | D32: =IF(Property_Info!$B$8>0,B32/Property_Info!$B$8,0) | E32: =IF(Property_Info!$B$23>0,B32/Property_Info!$B$23,0)
A34: OTHER EXPENSES
A35: Security | C35: =IF(Property_Info!$B$7>0,B35/Property_Info!$B$7,0) | D35: =IF(Property_Info!$B$8>0,B35/Property_Info!$B$8,0) | E35: =IF(Property_Info!$B$23>0,B35/Property_Info!$B$23,0)
A36: Elevator Service | C36: =IF(Property_Info!$B$7>0,B36/Property_Info!$B$7,0) | D36: =IF(Property_Info!$B$8>0,B36/Property_Info!$B$8,0) | E36: =IF(Property_Info!$B$23>0,B36/Property_Info!$B$23,0)
A37: License/Permits | C37: =IF(Property_Info!$B$7>0,B37/Property_Info!$B$7,0) | D37: =IF(Property_Info!$B$8>0,B37/Property_Info!$B$8,0) | E37: =IF(Property_Info!$B$23>0,B37/Property_Info!$B$23,0)
A38: Miscellaneous | C38: =IF(Property_Info!$B$7>0,B38/Property_Info!$B$7,0) | D38: =IF(Property_Info!$B$8>0,B38/Property_Info!$B$8,0) | E38: =IF(Property_Info!$B$23>0,B38/Property_Info!$B$23,0)
A39: TOTAL OPERATING EXPENSES | B39: =SUM(B5:B38) | C39: =IF(Property_Info!$B$7>0,B39/Property_Info!$B$7,0) | D39: =IF(Property_Info!$B$8>0,B39/Property_Info!$B$8,0) | E39: =IF(Property_Info!$B$23>0,B39/Property_Info!$B$23,0)
A41: KEY METRICS
A42: Operating Expense Ratio: | B42: =B39/Property_Info!$B$23
A43: OpEx Per Unit: | B43: =B39/Property_Info!$B$7
A44: OpEx Per SF: | B44: =B39/Property_Info!$B$8

Sheet Benchmark_Comparison
A1: BENCHMARK COMPARISON ANALYSIS
A2: Compare your expenses to industry benchmarks. Red = above market, Green = below market.
A4: Expense Category | B4: Your Actual | C4: Market Low | D4: Market Avg | E4: Market High | F4: Variance | G4: Status
A5: Property Taxes | B5: =Actual_Expenses!C6 | C5: 400 | D5: 800 | E5: 1500 | F5: =B5-D5 | G5: =IF(B5<=D5,"Below Market","Above Market")
A6: Property Insurance | B6: =Actual_Expenses!C7 | C6: 200 | D6: 400 | E6: 800 | F6: =B6-D6 | G6: =IF(B6<=D6,"Below Market","Above Market")
A7: Property Management | B7: =Actual_Expenses!C11 | C7: 300 | D7: 600 | E7: 1200 | F7: =B7-D7 | G7: =IF(B7<=D7,"Below Market","Above Market")
A8: Repairs & Maintenance | B8: =Actual_Expenses!C13 | C8: 500 | D8: 900 | E8: 1500 | F8: =B8-D8 | G8: =IF(B8<=D8,"Below Market","Above Market")
A9: Utilities (total) | B9: =SUM(Actual_Expenses!C17:C20) | C9: 200 | D9: 450 | E9: 900 | F9: =B9-D9 | G9: =IF(B9<=D9,"Below Market","Above Market")
A10: Landscaping/Grounds | B10: =Actual_Expenses!C23 | C10: 100 | D10: 250 | E10: 500 | F10: =B10-D10 | G10: =IF(B10<=D10,"Below Market","Above Market")
A11: Administrative | B11: =SUM(Actual_Expenses!C28:C31) | C11: 100 | D11: 200 | E11: 400 | F11: =B11-D11 | G11: =IF(B11<=D11,"Below Market","Above Market")
A13: TOTAL OpEx Per Unit | B13: =Actual_Expenses!C39 | C13: 3000 | D13: 4500 | E13: 7000 | F13: =B13-D13 | G13: =IF(B13<=D13,"Below Market","Above Market")
A15: OPEX RATIO BENCHMARK
A16: Property Class | B16: Your OpEx Ratio | C16: Target Range | D16: Assessment
A17: =Property_Info!B12 | B17: =Actual_Expenses!B42

Sheet 5_Year_Projections
A1: 5-YEAR OPERATING EXPENSE PROJECTIONS
A2: Project operating expenses over 5-year hold period. Enter annual growth rates below.
A4: ANNUAL GROWTH ASSUMPTIONS
A5: Property Tax Growth %: | B5: 3
A6: Insurance Growth %: | B6: 4
A7: General Expense Growth %: | B7: 3
A9: Expense Category | B9: Year 1 | C9: Year 2 | D9: Year 3 | E9: Year 4 | F9: Year 5
A10: Property Taxes | B10: =Actual_Expenses!B6 | C10: =B10*(1+$B5) | D10: =C10*(1+$B5) | E10: =D10*(1+$B5) | F10: =E10*(1+$B5)
A11: Property Insurance | B11: =Actual_Expenses!B7 | C11: =B11*(1+$B6) | D11: =C11*(1+$B6) | E11: =D11*(1+$B6) | F11: =E11*(1+$B6)
A12: HOA/Condo Fees | B12: =Actual_Expenses!B8 | C12: =B12*(1+$B7) | D12: =C12*(1+$B7) | E12: =D12*(1+$B7) | F12: =E12*(1+$B7)
A13: Property Management | B13: =Actual_Expenses!B11 | C13: =B13*(1+$B7) | D13: =C13*(1+$B7) | E13: =D13*(1+$B7) | F13: =E13*(1+$B7)
A14: Leasing/Marketing | B14: =Actual_Expenses!B12 | C14: =B14*(1+$B7) | D14: =C14*(1+$B7) | E14: =D14*(1+$B7) | F14: =E14*(1+$B7)
A15: Repairs & Maintenance | B15: =Actual_Expenses!B13 | C15: =B15*(1+$B7) | D15: =C15*(1+$B7) | E15: =D15*(1+$B7) | F15: =E15*(1+$B7)
A16: Turnover Costs | B16: =Actual_Expenses!B14 | C16: =B16*(1+$B7) | D16: =C16*(1+$B7) | E16: =D16*(1+$B7) | F16: =E16*(1+$B7)
A17: Water & Sewer | B17: =Actual_Expenses!B17 | C17: =B17*(1+$B7) | D17: =C17*(1+$B7) | E17: =D17*(1+$B7) | F17: =E17*(1+$B7)
A18: Trash Removal | B18: =Actual_Expenses!B18 | C18: =B18*(1+$B7) | D18: =C18*(1+$B7) | E18: =D18*(1+$B7) | F18: =E18*(1+$B7)
A19: Electric (common) | B19: =Actual_Expenses!B19 | C19: =B19*(1+$B7) | D19: =C19*(1+$B7) | E19: =D19*(1+$B7) | F19: =E19*(1+$B7)
A20: Gas (common) | B20: =Actual_Expenses!B20 | C20: =B20*(1+$B7) | D20: =C20*(1+$B7) | E20: =D20*(1+$B7) | F20: =E20*(1+$B7)
A21: Landscaping | B21: =Actual_Expenses!B23 | C21: =B21*(1+$B7) | D21: =C21*(1+$B7) | E21: =D21*(1+$B7) | F21: =E21*(1+$B7)
A22: Snow Removal | B22: =Actual_Expenses!B24 | C22: =B22*(1+$B7) | D22: =C22*(1+$B7) | E22: =D22*(1+$B7) | F22: =E22*(1+$B7)
A23: Pest Control | B23: =Actual_Expenses!B25 | C23: =B23*(1+$B7) | D23: =C23*(1+$B7) | E23: =D23*(1+$B7) | F23: =E23*(1+$B7)
A24: Pool/Spa Service | B24: =Actual_Expenses!B26 | C24: =B24*(1+$B7) | D24: =C24*(1+$B7) | E24: =D24*(1+$B7) | F24: =E24*(1+$B7)
A25: Accounting | B25: =Actual_Expenses!B28 | C25: =B25*(1+$B7) | D25: =C25*(1+$B7) | E25: =D25*(1+$B7) | F25: =E25*(1+$B7)
A26: Legal Fees | B26: =Actual_Expenses!B29 | C26: =B26*(1+$B7) | D26: =C26*(1+$B7) | E26: =D26*(1+$B7) | F26: =E26*(1+$B7)
A27: Office Supplies | B27: =Actual_Expenses!B30 | C27: =B27*(1+$B7) | D27: =C27*(1+$B7) | E27: =D27*(1+$B7) | F27: =E27*(1+$B7)
A28: Professional Fees | B28: =Actual_Expenses!B31 | C28: =B28*(1+$B7) | D28: =C28*(1+$B7) | E28: =D28*(1+$B7) | F28: =E28*(1+$B7)
A29: Security | B29: =Actual_Expenses!B33 | C29: =B29*(1+$B7) | D29: =C29*(1+$B7) | E29: =D29*(1+$B7) | F29: =E29*(1+$B7)
A30: Elevator Service | B30: =Actual_Expenses!B34 | C30: =B30*(1+$B7) | D30: =C30*(1+$B7) | E30: =D30*(1+$B7) | F30: =E30*(1+$B7)
A31: License/Permits | B31: =Actual_Expenses!B35 | C31: =B31*(1+$B7) | D31: =C31*(1+$B7) | E31: =D31*(1+$B7) | F31: =E31*(1+$B7)
A32: Miscellaneous | B32: =Actual_Expenses!B36 | C32: =B32*(1+$B7) | D32: =C32*(1+$B7) | E32: =D32*(1+$B7) | F32: =E32*(1+$B7)
A33: TOTAL OPERATING EXPENSES | B33: =SUM(B10:B32) | C33: =SUM(C10:C32) | D33: =SUM(D10:D32) | E33: =SUM(E10:E32) | F33: =SUM(F10:F32)
A35: KEY METRICS OVER TIME
A36: OpEx Per Unit | B36: =B33/Property_Info!$B$7 | C36: =C33/Property_Info!$B$7 | D36: =D33/Property_Info!$B$7 | E36: =E33/Property_Info!$B$7 | F36: =F33/Property_Info!$B$7
A37: OpEx Growth Rate % | B37: N/A | C37: =(C33/B33)-1 | D37: =(D33/C33)-1 | E37: =(E33/D33)-1 | F37: =(F33/E33)-1
